INSTALL.rst
LICENSE
MANIFEST.in
README.rst
VERSION
requirements.txt
setup.cfg
setup.py
tasks.py
src/hope_of_ropes/__init__.py
src/hope_of_ropes/__main__.py
src/hope_of_ropes/__meta__.py
src/hope_of_ropes/elastic.py
src/hope_of_ropes/enemy.py
src/hope_of_ropes/light.py
src/hope_of_ropes/light_simul.py
src/hope_of_ropes/main_menu.py
src/hope_of_ropes/music.py
src/hope_of_ropes/number.py
src/hope_of_ropes/platforms.py
src/hope_of_ropes/player.py
src/hope_of_ropes/rope.py
src/hope_of_ropes/signals.py
src/hope_of_ropes.egg-info/PKG-INFO
src/hope_of_ropes.egg-info/SOURCES.txt
src/hope_of_ropes.egg-info/dependency_links.txt
src/hope_of_ropes.egg-info/entry_points.txt
src/hope_of_ropes.egg-info/not-zip-safe
src/hope_of_ropes.egg-info/requires.txt
src/hope_of_ropes.egg-info/top_level.txt
src/hope_of_ropes/tests/__init__.py
src/hope_of_ropes/tests/__main__.py
src/hope_of_ropes/tests/test_documentation.py
src/hope_of_ropes/tests/test_hope_of_ropes.py