Metadata-Version: 1.1
Name: hope-of-ropes
Version: 0.2.8
Summary: Game of hour.
Home-page: https://github.com/fis-jogos/ep1-time-daora
Author: Time Daora
Author-email: felipe.osorio72@outlook.com.br
License: UNKNOWN
Platform: any
Classifier: Development Status :: 3 - Alpha
Classifier: Intended Audience :: Developers
Classifier: License :: OSI Approved :: GNU General Public License (GPL)
Classifier: Operating System :: OS Independent
Classifier: Programming Language :: Python
Classifier: Programming Language :: Python :: 3
Classifier: Programming Language :: Python :: 3.3
Classifier: Programming Language :: Python :: 3.4
Classifier: Programming Language :: Python :: 3.5
